kis_uid_generator_utils/__init__.py
kis_uid_generator_utils/console_helper.py
kis_uid_generator_utils/constants.py
kis_uid_generator_utils/file_utils.py
kis_uid_generator_utils/generator.py
kis_uid_generator_utils/system_caller.py
kis_uid_generator_utils/conf/config.yaml
kis_uid_generator_utils-0.1.1.dist-info/AUTHORS.rst
kis_uid_generator_utils-0.1.1.dist-info/METADATA
kis_uid_generator_utils-0.1.1.dist-info/WHEEL
kis_uid_generator_utils-0.1.1.dist-info/entry_points.txt
kis_uid_generator_utils-0.1.1.dist-info/top_level.txt
kis_uid_generator_utils-0.1.1.dist-info/RECORD
