Metadata-Version: 2.2
Name: kis_uid_generator_utils
Version: 0.1.1
Summary: Collection of Python modules for generating unique identifiers.
Author-email: Jaideep Sundaram <jai.python3@gmail.com>
Maintainer-email: Jaideep Sundaram <jai.python3@gmail.com>
License: Not open source
Project-URL: Homepage, https://github.com/jai-python3/kis-uid-generator-utils
Keywords: kis_uid_generator_utils
Classifier: Development Status :: 5 - Production/Stable
Classifier: Intended Audience :: Developers
Classifier: Natural Language :: English
Classifier: Programming Language :: Python :: 3.10
Requires-Python: >=3.10
License-File: AUTHORS.rst
Requires-Dist: Click>=7.0
Requires-Dist: PyYAML
Requires-Dist: Rich
Requires-Dist: singleton-decorator
Provides-Extra: dev
Requires-Dist: pytest>=6.2; extra == "dev"
Requires-Dist: pytest-mock>=3.6; extra == "dev"
Requires-Dist: coverage>=5.5; extra == "dev"
